orchard_client.py
orchard_python_client-1.0.0.dist-info/METADATA
orchard_python_client-1.0.0.dist-info/WHEEL
orchard_python_client-1.0.0.dist-info/top_level.txt
orchard_python_client-1.0.0.dist-info/RECORD
